unibreak-0.2.0.dist-info/METADATA
unibreak-0.2.0.dist-info/WHEEL
unibreak/__init__.py
unibreak/__init__.pyi
unibreak/py.typed
unibreak/unibreak.cpython-312-aarch64-linux-gnu.so
unibreak-0.2.0.dist-info/RECORD
