Metadata-Version: 2.4
Name: unibreak
Version: 0.2.0
Classifier: Programming Language :: Rust
Classifier: Programming Language :: Python :: Implementation :: CPython
Classifier: Programming Language :: Python :: Implementation :: PyPy
Summary: Python bindings for unicode-segmentation Rust crate
Author: Cline
License: MIT
Requires-Python: >=3.8
